imageZIP/__init__.py
imageZIP/imageZIP.py
imageZIP-3.1.dist-info/LICENSE
imageZIP-3.1.dist-info/METADATA
imageZIP-3.1.dist-info/WHEEL
imageZIP-3.1.dist-info/top_level.txt
imageZIP-3.1.dist-info/RECORD
