Metadata-Version: 2.1
Name: imageZIP
Version: 3.1
Summary: Archive (encrypt) files and directories to image file
Home-page: http://github.com/hermanTenuki/imageZIP/
Author: Herman Schechkin (hermanTenuki)
Author-email: itseasy322@gmail.com
License: MIT
Platform: UNKNOWN
Classifier: Development Status :: 5 - Production/Stable
Classifier: Environment :: Console
Classifier: Intended Audience :: Developers
Classifier: License :: OSI Approved :: MIT License
Classifier: Programming Language :: Python :: 3
Classifier: Programming Language :: Python :: Implementation :: CPython
Classifier: Operating System :: OS Independent
Classifier: Topic :: Scientific/Engineering :: Image Processing
Classifier: Topic :: Scientific/Engineering :: Visualization
Classifier: Topic :: Security :: Cryptography
Requires-Python: >=3
Requires-Dist: Pillow
